{
  "main": {
    "id": "656e4ec33c86213f",
    "type": "split",
    "children": [
      {
        "id": "caa82487e79f5a52",
        "type": "tabs",
        "children": [
          {
            "id": "67feed4927d2ac7f",
            "type": "leaf",
            "state": {
              "type": "markdown",
              "state": {
                "file": "Springs Eternal.md",
                "mode": "source",
                "source": false,
                "backlinks": true,
                "backlinkOpts": {
                  "collapseAll": false,
                  "extraContext": false,
                  "sortOrder": "alphabetical",
                  "showSearch": false,
                  "searchQuery": "",
                  "backlinkCollapsed": false,
                  "unlinkedCollapsed": true
                }
              },
              "icon": "lucide-file",
              "title": "Springs Eternal"
            }
          },
          {
            "id": "cb697a11f32974df",
            "type": "leaf",
            "state": {
              "type": "map",
              "state": {
                "name": "Default",
                "mapZoom": 19,
                "mapCenter": {
                  "lat": 52.95609069564848,
                  "lng": -1.1496052511951362
                },
                "query": "",
                "queryError": false,
                "chosenMapSource": 0,
                "forceHistorySave": false,
                "followActiveNote": false,
                "embeddedHeight": 300,
                "autoFit": false,
                "lock": false,
                "showLinks": false,
                "linkColor": "red",
                "markerLabels": "off"
              },
              "icon": "map-pin",
              "title": "Interactive Map View"
            }
          },
          {
            "id": "a15a2f96c71b3ee7",
            "type": "leaf",
            "state": {
              "type": "markdown",
              "state": {
                "file": "Tryptik Café.md",
                "mode": "source",
                "source": false,
                "backlinks": true,
                "backlinkOpts": {
                  "collapseAll": false,
                  "extraContext": false,
                  "sortOrder": "alphabetical",
                  "showSearch": false,
                  "searchQuery": "",
                  "backlinkCollapsed": false,
                  "unlinkedCollapsed": true
                }
              },
              "icon": "lucide-file",
              "title": "Tryptik Café"
            }
          }
        ],
        "currentTab": 2
      },
      {
        "id": "9e122331f0522f42",
        "type": "tabs",
        "children": [
          {
            "id": "2519d709b79b4a5a",
            "type": "leaf",
            "state": {
              "type": "markdown",
              "state": {
                "file": "FOUNT - medispa.md",
                "mode": "source",
                "source": false,
                "backlinks": true,
                "backlinkOpts": {
                  "collapseAll": false,
                  "extraContext": false,
                  "sortOrder": "alphabetical",
                  "showSearch": false,
                  "searchQuery": "",
                  "backlinkCollapsed": false,
                  "unlinkedCollapsed": true
                }
              },
              "icon": "lucide-file",
              "title": "FOUNT - medispa"
            }
          },
          {
            "id": "261dfa78088a6504",
            "type": "leaf",
            "state": {
              "type": "markdown",
              "state": {
                "file": "Trinity Square.md",
                "mode": "source",
                "source": false,
                "backlinks": true,
                "backlinkOpts": {
                  "collapseAll": false,
                  "extraContext": false,
                  "sortOrder": "alphabetical",
                  "showSearch": false,
                  "searchQuery": "",
                  "backlinkCollapsed": false,
                  "unlinkedCollapsed": true
                }
              },
              "icon": "lucide-file",
              "title": "Trinity Square"
            }
          }
        ]
      }
    ],
    "direction": "vertical"
  },
  "left": {
    "id": "2ebddbd92a19d235",
    "type": "split",
    "children": [
      {
        "id": "a1400607499e03b0",
        "type": "tabs",
        "children": [
          {
            "id": "536d172cb798ba27",
            "type": "leaf",
            "state": {
              "type": "file-explorer",
              "state": {
                "sortOrder": "alphabetical",
                "autoReveal": false
              },
              "icon": "lucide-folder-closed",
              "title": "Files"
            }
          },
          {
            "id": "375edfeac42b5b13",
            "type": "leaf",
            "state": {
              "type": "search",
              "state": {
                "query": "tag:#relationship",
                "matchingCase": false,
                "explainSearch": false,
                "collapseAll": false,
                "extraContext": false,
                "sortOrder": "alphabetical"
              },
              "icon": "lucide-search",
              "title": "Search"
            }
          },
          {
            "id": "23f0fd28fb8b6770",
            "type": "leaf",
            "state": {
              "type": "bookmarks",
              "state": {},
              "icon": "lucide-bookmark",
              "title": "Bookmarks"
            }
          }
        ]
      }
    ],
    "direction": "horizontal",
    "width": 300
  },
  "right": {
    "id": "847fa648e9e33dd5",
    "type": "split",
    "children": [
      {
        "id": "9edc5162860a3eab",
        "type": "tabs",
        "children": [
          {
            "id": "bf13e47fd79297d6",
            "type": "leaf",
            "state": {
              "type": "backlink",
              "state": {
                "file": "Attachments/missionreport.pdf",
                "collapseAll": false,
                "extraContext": false,
                "sortOrder": "alphabetical",
                "showSearch": false,
                "searchQuery": "",
                "backlinkCollapsed": false,
                "unlinkedCollapsed": true
              },
              "icon": "links-coming-in",
              "title": "Backlinks for missionreport"
            }
          },
          {
            "id": "b814a180846b83c4",
            "type": "leaf",
            "state": {
              "type": "outgoing-link",
              "state": {
                "file": "Nottingham Branch.md",
                "linksCollapsed": false,
                "unlinkedCollapsed": true
              },
              "icon": "links-going-out",
              "title": "Outgoing links from Nottingham Branch"
            }
          },
          {
            "id": "5f9bf293389353d9",
            "type": "leaf",
            "state": {
              "type": "tag",
              "state": {
                "sortOrder": "frequency",
                "useHierarchy": true,
                "showSearch": false,
                "searchQuery": ""
              },
              "icon": "lucide-tags",
              "title": "Tags"
            }
          },
          {
            "id": "4c3f52bce16781f6",
            "type": "leaf",
            "state": {
              "type": "outline",
              "state": {
                "file": "Nottingham Branch.md",
                "followCursor": false,
                "showSearch": false,
                "searchQuery": ""
              },
              "icon": "lucide-list",
              "title": "Outline of Nottingham Branch"
            }
          },
          {
            "id": "e02fea582116945a",
            "type": "leaf",
            "state": {
              "type": "DICE_ROLLER_VIEW",
              "state": {},
              "icon": "dices",
              "title": "Dice Tray"
            }
          },
          {
            "id": "a1839e5aa698144d",
            "type": "leaf",
            "state": {
              "type": "PROGRESS_CLOCKS_VIEW",
              "state": {},
              "icon": "pie-chart",
              "title": "Progress Clocks"
            }
          }
        ]
      }
    ],
    "direction": "horizontal",
    "width": 300,
    "collapsed": true
  },
  "left-ribbon": {
    "hiddenItems": {
      "switcher:Open quick switcher": false,
      "graph:Open graph view": false,
      "canvas:Create new canvas": false,
      "daily-notes:Open today's daily note": false,
      "templates:Insert template": false,
      "command-palette:Open command palette": false,
      "obsidian-map-view:Open map view": false,
      "obsidian-excalidraw-plugin:New drawing": false,
      "obsidian-kanban:Create new board": false
    }
  },
  "active": "2519d709b79b4a5a",
  "lastOpenFiles": [
    "Tryptik Café.md",
    "Baron Everly.md",
    "Trinity Square.md",
    "Attachments/Pasted image 20250507225627.png",
    "FOUNT - medispa.md",
    "Springs Eternal.md",
    "Passionfruit Anomaly.md",
    "Olive Huyhn.md",
    "Passionfruit Anomaly Chaos Effects.md",
    "Attachments/Pasted image 20250507220041.png",
    "Orville Herring.md",
    "Kelb Cambrian.md",
    "Kaeleigh \"K\" Merel.md",
    "Jenny Drops.md",
    "Gregory.md",
    "Downwards Facing Dawg.md",
    "Kubra Omowale.md",
    "Field Team 3.md",
    "Eevesijika.md",
    "Drew.md",
    "Kirsty.md",
    "Destiny Summer.md",
    "Ice Cream Shop Boss - Randal Ballad.md",
    "Obsessed Roommate - Cathy.md",
    "Granny Clementine.md",
    "Olivia Barns.md",
    "Chivonne Inpu.md",
    "Attachments/missionreport.pdf",
    "Attachments/Kaeleigh_Headshot_Coloured.png",
    "Untitled.canvas",
    "Attachments/missionreport 1.pdf",
    "Attachments/Pasted image 20250421133206.png",
    "Attachments/missionreport.png",
    "Excalidraw",
    "Attachments/IMG_0486.jpeg",
    "Attachments",
    "Pasted image 20250317165035.png"
  ]
}